static_view/__init__.py
static_view/startserver.py
static_view/core/__init__.py
static_view/core/filename.py
static_view/core/request_handler.py
static_view/core/settings.py
static_view_berk_erdemoglu-0.0.2.dist-info/LICENSE
static_view_berk_erdemoglu-0.0.2.dist-info/METADATA
static_view_berk_erdemoglu-0.0.2.dist-info/WHEEL
static_view_berk_erdemoglu-0.0.2.dist-info/top_level.txt
static_view_berk_erdemoglu-0.0.2.dist-info/RECORD
